pyzkaccess/__init__.py
pyzkaccess/_setup.py
pyzkaccess/aux_input.py
pyzkaccess/cli.py
pyzkaccess/common.py
pyzkaccess/ctypes_.py
pyzkaccess/device.py
pyzkaccess/device_data/__init__.py
pyzkaccess/device_data/model.py
pyzkaccess/device_data/queryset.py
pyzkaccess/door.py
pyzkaccess/enums.py
pyzkaccess/event.py
pyzkaccess/exceptions.py
pyzkaccess/main.py
pyzkaccess/param.py
pyzkaccess/reader.py
pyzkaccess/relay.py
pyzkaccess/sdk.py
pyzkaccess/tables.py
pyzkaccess-1.1.dist-info/LICENSE
pyzkaccess-1.1.dist-info/METADATA
pyzkaccess-1.1.dist-info/WHEEL
pyzkaccess-1.1.dist-info/entry_points.txt
pyzkaccess-1.1.dist-info/RECORD
