Metadata-Version: 2.1
Name: pyzkaccess
Version: 1.1
Summary: Library and CLI tool for working with ZKTeco ZKAccess C3-100/200/400 controllers
Home-page: https://github.com/bdragon300/pyzkaccess
License: Apache-2.0
Keywords: zkaccess,zkteco,c3-100,c3-200,c3-400,access control,door controller,zkaccess control
Author: Igor Derkach
Author-email: gosha753951@gmail.com
Requires-Python: >=3.8,<4.0
Classifier: Development Status :: 4 - Beta
Classifier: Intended Audience :: Customer Service
Classifier: Intended Audience :: Developers
Classifier: Intended Audience :: Telecommunications Industry
Classifier: License :: OSI Approved :: Apache Software License
Classifier: Operating System :: Microsoft :: Windows
Classifier: Programming Language :: Python :: 3
Classifier: Programming Language :: Python :: 3.8
Classifier: Programming Language :: Python :: 3.9
Classifier: Programming Language :: Python :: 3.10
Classifier: Programming Language :: Python :: 3.11
Classifier: Programming Language :: Python :: 3.12
Classifier: Programming Language :: Python :: 3.13
Classifier: Topic :: System :: Hardware
Requires-Dist: fire (>=0.7.0,<0.8.0)
Requires-Dist: prettytable (>=3.11.0,<4.0.0)
Requires-Dist: wrapt (>=1.16.0,<2.0.0)
Project-URL: Documentation, https://bdragon300.github.io/pyzkaccess/
Project-URL: Repository, https://github.com/bdragon300/pyzkaccess
